{
  "todos": [
    {
      "id": 1,
      "title": "json-server",
      "status": false
    },
    {
      "title": "gg",
      "status": false,
      "id": 2
    },
    {
      "title": "555",
      "status": false,
      "id": 3
    },
    {
      "title": "",
      "status": false,
      "id": 4
    },
    {
      "title": "",
      "status": false,
      "id": 5
    },
    {
      "title": "",
      "status": false,
      "id": 6
    },
    {
      "title": "",
      "status": false,
      "id": 7
    },
    {
      "title": "",
      "status": false,
      "id": 8
    }
  ]
}